{
  "headers": [
    {
      "tool_name": "scancode-toolkit",
      "tool_version": "32.5.0",
      "options": {
        "input": [
          "C:\\Users\\Bonelli\\PycharmProjects\\analisi-etica-codice-ai\\data\\files\\3210325463\\after"
        ],
        "--copyright": true,
        "--ignore": [
          "*vendor__*",
          "*node_modules__*",
          "*third_party__*",
          "*thirdparty__*",
          "*external__*",
          "*__proto__*",
          "*__generated__*",
          "*_pb2*",
          "*.pb.*",
          "*__gen__*",
          "*autogenerated*",
          "*auto_generated*",
          "*public__js__*",
          "*dist__*",
          "*build__*",
          "*__bundle*",
          "*.min.*"
        ],
        "--info": true,
        "--json-pp": "C:\\Users\\Bonelli\\PycharmProjects\\analisi-etica-codice-ai\\results\\ip_rights\\scancode_raw\\3210325463.json",
        "--license": true,
        "--processes": "2"
      },
      "notice": "Generated with ScanCode and provided on an \"AS IS\" BASIS, WITHOUT WARRANTIES\nOR CONDITIONS OF ANY KIND, either express or implied. No content created from\nScanCode should be considered or used as legal advice. Consult an Attorney\nfor any legal advice.\nScanCode is a free software code scanning tool from nexB Inc. and others.\nVisit https://github.com/nexB/scancode-toolkit/ for support and download.",
      "start_timestamp": "2026-07-22T133726.016779",
      "end_timestamp": "2026-07-22T133744.743242",
      "output_format_version": "4.1.0",
      "duration": 18.726483821868896,
      "message": null,
      "errors": [],
      "warnings": [],
      "extra_data": {
        "system_environment": {
          "operating_system": "win",
          "cpu_architecture": "64",
          "platform": "Windows-10-10.0.19045-SP0",
          "platform_version": "10.0.19045",
          "python_version": "3.14.6 (tags/v3.14.6:c63aec6, Jun 10 2026, 10:26:10) [MSC v.1944 64 bit (AMD64)]"
        },
        "spdx_license_list_version": "3.27",
        "files_count": 44
      }
    }
  ],
  "license_detections": [
    {
      "identifier": "mit-3fce6ea2-8abd-6c6b-3ede-a37af7c6efee",
      "license_expression": "mit",
      "license_expression_spdx": "MIT",
      "detection_count": 1,
      "reference_matches": [
        {
          "license_expression": "mit",
          "license_expression_spdx": "MIT",
          "from_file": "after/Cargo__1b290eb3.toml",
          "start_line": 50,
          "end_line": 50,
          "matcher": "2-aho",
          "score": 100.0,
          "matched_length": 2,
          "match_coverage": 100.0,
          "rule_relevance": 100,
          "rule_identifier": "mit_30.RULE",
          "rule_url": "https://github.com/nexB/scancode-toolkit/tree/develop/src/licensedcode/data/rules/mit_30.RULE"
        }
      ]
    }
  ],
  "files": [
    {
      "path": "after",
      "type": "directory",
      "name": "after",
      "base_name": "after",
      "extension": "",
      "size": 0,
      "date": null,
      "sha1": null,
      "md5": null,
      "sha256": null,
      "sha1_git": null,
      "mime_type": null,
      "file_type": null,
      "programming_language": null,
      "is_binary": false,
      "is_text": false,
      "is_archive": false,
      "is_media": false,
      "is_source": false,
      "is_script": false,
      "detected_license_expression": null,
      "detected_license_expression_spdx": null,
      "license_detections": [],
      "license_clues": [],
      "percentage_of_license_text": 0,
      "copyrights": [],
      "holders": [],
      "authors": [],
      "files_count": 44,
      "dirs_count": 0,
      "size_count": 242342,
      "scan_errors": []
    },
    {
      "path": "after/Cargo__14a5af75.lock",
      "type": "file",
      "name": "Cargo__14a5af75.lock",
      "base_name": "Cargo__14a5af75",
      "extension": ".lock",
      "size": 62905,
      "date": "2026-07-20",
      "sha1": "69f0cf5b8aa231a512a40adf5a02df94b8fc666f",
      "md5": "7bb2f1c8092a466a5b247350ba9aba76",
      "sha256": "61a5bf9957526ef8b7e61ac9c93dac1815389a7e82a7696e3b3eb279493c3a0a",
      "sha1_git": "1382411367a758404f24af1f3be116b27d0c8e5a",
      "mime_type": "text/plain",
      "file_type": "ASCII text",
      "programming_language": null,
      "is_binary": false,
      "is_text": true,
      "is_archive": false,
      "is_media": false,
      "is_source": false,
      "is_script": false,
      "detected_license_expression": null,
      "detected_license_expression_spdx": null,
      "license_detections": [],
      "license_clues": [],
      "percentage_of_license_text": 0,
      "copyrights": [],
      "holders": [],
      "authors": [],
      "files_count": 0,
      "dirs_count": 0,
      "size_count": 0,
      "scan_errors": []
    },
    {
      "path": "after/Cargo__1b290eb3.toml",
      "type": "file",
      "name": "Cargo__1b290eb3.toml",
      "base_name": "Cargo__1b290eb3",
      "extension": ".toml",
      "size": 2445,
      "date": "2026-07-20",
      "sha1": "93852eb891932c48b717d9620f92c7141873ee24",
      "md5": "18ef6a9588f1fc6c291df2ca03e7e43f",
      "sha256": "afc2b06320c28b59677aa6a501f94e2720c967c8499b3394fdf080d43c9d5757",
      "sha1_git": "f8d6c5711988d4658f178fdde1f44556a61ff660",
      "mime_type": "text/plain",
      "file_type": "ASCII text",
      "programming_language": null,
      "is_binary": false,
      "is_text": true,
      "is_archive": false,
      "is_media": false,
      "is_source": false,
      "is_script": false,
      "detected_license_expression": "mit",
      "detected_license_expression_spdx": "MIT",
      "license_detections": [
        {
          "license_expression": "mit",
          "license_expression_spdx": "MIT",
          "matches": [
            {
              "license_expression": "mit",
              "license_expression_spdx": "MIT",
              "from_file": "after/Cargo__1b290eb3.toml",
              "start_line": 50,
              "end_line": 50,
              "matcher": "2-aho",
              "score": 100.0,
              "matched_length": 2,
              "match_coverage": 100.0,
              "rule_relevance": 100,
              "rule_identifier": "mit_30.RULE",
              "rule_url": "https://github.com/nexB/scancode-toolkit/tree/develop/src/licensedcode/data/rules/mit_30.RULE"
            }
          ],
          "identifier": "mit-3fce6ea2-8abd-6c6b-3ede-a37af7c6efee"
        }
      ],
      "license_clues": [],
      "percentage_of_license_text": 0.62,
      "copyrights": [],
      "holders": [],
      "authors": [],
      "files_count": 0,
      "dirs_count": 0,
      "size_count": 0,
      "scan_errors": []
    },
    {
      "path": "after/CONFIGURE__0f800ae6.md",
      "type": "file",
      "name": "CONFIGURE__0f800ae6.md",
      "base_name": "CONFIGURE__0f800ae6",
      "extension": ".md",
      "size": 8829,
      "date": "2026-07-20",
      "sha1": "3d8cd72529183663024a6b62406d773e7d32cad9",
      "md5": "4f9c6c95a95b624c0e265ad800f33765",
      "sha256": "99beb6e845cbf6d42eb123e0d9a6471feaf46b5e594677627f29edd9d45d91b5",
      "sha1_git": "92dd771b6d005bbbcb44be23b750e498718d5551",
      "mime_type": "text/plain",
      "file_type": "ASCII text",
      "programming_language": null,
      "is_binary": false,
      "is_text": true,
      "is_archive": false,
      "is_media": false,
      "is_source": false,
      "is_script": false,
      "detected_license_expression": null,
      "detected_license_expression_spdx": null,
      "license_detections": [],
      "license_clues": [],
      "percentage_of_license_text": 0,
      "copyrights": [],
      "holders": [],
      "authors": [],
      "files_count": 0,
      "dirs_count": 0,
      "size_count": 0,
      "scan_errors": []
    },
    {
      "path": "after/core-lib__Cargo__a826488e.toml",
      "type": "file",
      "name": "core-lib__Cargo__a826488e.toml",
      "base_name": "core-lib__Cargo__a826488e",
      "extension": ".toml",
      "size": 550,
      "date": "2026-07-20",
      "sha1": "19c7c9656ec14fcac3f68517427c22c0cb7b8b01",
      "md5": "854f469257b80fe15d409a13e31e8207",
      "sha256": "90b4f6988e01e954fd18cea498d47bd3a98fffd4f02c8aadac428962852301e9",
      "sha1_git": "d427d0c1dd2f3322f5173faeaa00b27a9b26ce49",
      "mime_type": "text/plain",
      "file_type": "ASCII text",
      "programming_language": null,
      "is_binary": false,
      "is_text": true,
      "is_archive": false,
      "is_media": false,
      "is_source": false,
      "is_script": false,
      "detected_license_expression": null,
      "detected_license_expression_spdx": null,
      "license_detections": [],
      "license_clues": [],
      "percentage_of_license_text": 0,
      "copyrights": [],
      "holders": [],
      "authors": [],
      "files_count": 0,
      "dirs_count": 0,
      "size_count": 0,
      "scan_errors": []
    },
    {
      "path": "after/core-lib__src__ini__0902f5a5.rs",
      "type": "file",
      "name": "core-lib__src__ini__0902f5a5.rs",
      "base_name": "core-lib__src__ini__0902f5a5",
      "extension": ".rs",
      "size": 9320,
      "date": "2026-07-20",
      "sha1": "4cf52fc38e3bc08537ca4dd1306a1d8dee5dbc2d",
      "md5": "311b3d19f4840227fdf4f83ef3f14c25",
      "sha256": "20c833f00c013459b6f2aaf9a2b00867e25579c9c7d6939b7da9469b7ca9b5cc",
      "sha1_git": "9b05c444be7952cab1f82b11afa3f03a78c45e96",
      "mime_type": "text/plain",
      "file_type": "ASCII text",
      "programming_language": "Rust",
      "is_binary": false,
      "is_text": true,
      "is_archive": false,
      "is_media": false,
      "is_source": true,
      "is_script": false,
      "detected_license_expression": null,
      "detected_license_expression_spdx": null,
      "license_detections": [],
      "license_clues": [],
      "percentage_of_license_text": 0,
      "copyrights": [],
      "holders": [],
      "authors": [],
      "files_count": 0,
      "dirs_count": 0,
      "size_count": 0,
      "scan_errors": []
    },
    {
      "path": "after/core-lib__src__listener__5a680606.rs",
      "type": "file",
      "name": "core-lib__src__listener__5a680606.rs",
      "base_name": "core-lib__src__listener__5a680606",
      "extension": ".rs",
      "size": 3288,
      "date": "2026-07-20",
      "sha1": "3fa76e8c8a49c5200db4a3fe426838c0f8279df6",
      "md5": "ee191bda4a57e60b9e761e13af21b554",
      "sha256": "95d01fcbf2e61d8256299bf83e5e845ed8ea082a74a11957b0351353d42b1bff",
      "sha1_git": "b1b8aa67fff58c80c4e0fac8a4df354810c20c56",
      "mime_type": "text/plain",
      "file_type": "ASCII text",
      "programming_language": "Rust",
      "is_binary": false,
      "is_text": true,
      "is_archive": false,
      "is_media": false,
      "is_source": true,
      "is_script": false,
      "detected_license_expression": null,
      "detected_license_expression_spdx": null,
      "license_detections": [],
      "license_clues": [],
      "percentage_of_license_text": 0,
      "copyrights": [],
      "holders": [],
      "authors": [],
      "files_count": 0,
      "dirs_count": 0,
      "size_count": 0,
      "scan_errors": []
    },
    {
      "path": "after/core-lib__src__path__717bc847.rs",
      "type": "file",
      "name": "core-lib__src__path__717bc847.rs",
      "base_name": "core-lib__src__path__717bc847",
      "extension": ".rs",
      "size": 2620,
      "date": "2026-07-20",
      "sha1": "855cee81934fecb242779f18a77b9f2eaff3b6c7",
      "md5": "f85811b9aa3d5c95b45fa51014d2a81d",
      "sha256": "3b7ddb9839cef1761d9ea56bbe43ff588241e65ecbdc6a06c6f40df3b19250eb",
      "sha1_git": "0115b5231d0eb1c28e513d775ae1a746512d43a1",
      "mime_type": "text/plain",
      "file_type": "ASCII text",
      "programming_language": "Rust",
      "is_binary": false,
      "is_text": true,
      "is_archive": false,
      "is_media": false,
      "is_source": true,
      "is_script": false,
      "detected_license_expression": null,
      "detected_license_expression_spdx": null,
      "license_detections": [],
      "license_clues": [],
      "percentage_of_license_text": 0,
      "copyrights": [],
      "holders": [],
      "authors": [],
      "files_count": 0,
      "dirs_count": 0,
      "size_count": 0,
      "scan_errors": []
    },
    {
      "path": "after/core-lib__src__theme_icon_cache__97bec725.rs",
      "type": "file",
      "name": "core-lib__src__theme_icon_cache__97bec725.rs",
      "base_name": "core-lib__src__theme_icon_cache__97bec725",
      "extension": ".rs",
      "size": 3430,
      "date": "2026-07-20",
      "sha1": "81944b5c55a4f58e996f0a40ba1c68101cf66a54",
      "md5": "1f35bdec63f1cd6b753e00efe262e234",
      "sha256": "d5e1e35061ef171b01fe4fd3615dfd875536af2748938d49c5782eac1c3ffbf2",
      "sha1_git": "3134136b55c02fdb2bec3d01a0e4822d12b1ece9",
      "mime_type": "text/plain",
      "file_type": "ASCII text",
      "programming_language": "Rust",
      "is_binary": false,
      "is_text": true,
      "is_archive": false,
      "is_media": false,
      "is_source": true,
      "is_script": false,
      "detected_license_expression": null,
      "detected_license_expression_spdx": null,
      "license_detections": [],
      "license_clues": [],
      "percentage_of_license_text": 0,
      "copyrights": [],
      "holders": [],
      "authors": [],
      "files_count": 0,
      "dirs_count": 0,
      "size_count": 0,
      "scan_errors": []
    },
    {
      "path": "after/core-lib__src__util__default_desktop_file__ccd90f82.rs",
      "type": "file",
      "name": "core-lib__src__util__default_desktop_file__ccd90f82.rs",
      "base_name": "core-lib__src__util__default_desktop_file__ccd90f82",
      "extension": ".rs",
      "size": 757,
      "date": "2026-07-20",
      "sha1": "3cb1556ccf49b6b82ac9fe4db564c0474961d0e0",
      "md5": "2087211724941a4e2617daf35120d730",
      "sha256": "f7d3d47f8fcf42f242e1bd24e668225f2b13a8c4a82429cfc46258f9fa34bc24",
      "sha1_git": "d78fb64aae1dcfe604e26990f249324953b831b4",
      "mime_type": "text/plain",
      "file_type": "ASCII text",
      "programming_language": "Rust",
      "is_binary": false,
      "is_text": true,
      "is_archive": false,
      "is_media": false,
      "is_source": true,
      "is_script": false,
      "detected_license_expression": null,
      "detected_license_expression_spdx": null,
      "license_detections": [],
      "license_clues": [],
      "percentage_of_license_text": 0,
      "copyrights": [],
      "holders": [],
      "authors": [],
      "files_count": 0,
      "dirs_count": 0,
      "size_count": 0,
      "scan_errors": []
    },
    {
      "path": "after/core-lib__src__util__helpers__54ea4317.rs",
      "type": "file",
      "name": "core-lib__src__util__helpers__54ea4317.rs",
      "base_name": "core-lib__src__util__helpers__54ea4317",
      "extension": ".rs",
      "size": 2215,
      "date": "2026-07-20",
      "sha1": "a0fcdc3103c6d4b7af284d15e0a6a2d98c01a642",
      "md5": "cc2d1ff8daf135457041fd79bef42f7b",
      "sha256": "0d092682c76b136081f76530ea7cb58cace7fc88a27a3c55efa2a32df99e7770",
      "sha1_git": "678f0ba6447c2e0471091d5e4c85844d945c13e4",
      "mime_type": "text/plain",
      "file_type": "ASCII text",
      "programming_language": "Rust",
      "is_binary": false,
      "is_text": true,
      "is_archive": false,
      "is_media": false,
      "is_source": true,
      "is_script": false,
      "detected_license_expression": null,
      "detected_license_expression_spdx": null,
      "license_detections": [],
      "license_clues": [],
      "percentage_of_license_text": 0,
      "copyrights": [],
      "holders": [],
      "authors": [],
      "files_count": 0,
      "dirs_count": 0,
      "size_count": 0,
      "scan_errors": []
    },
    {
      "path": "after/core-lib__src__util__mod__c0c5cce0.rs",
      "type": "file",
      "name": "core-lib__src__util__mod__c0c5cce0.rs",
      "base_name": "core-lib__src__util__mod__c0c5cce0",
      "extension": ".rs",
      "size": 1591,
      "date": "2026-07-20",
      "sha1": "b84dec23e2941f7c3166f5ae7423f059c1958e21",
      "md5": "0eaef4b652104c82f572f98bb57e4acb",
      "sha256": "79acfe7043416d6317060f8b2967285c25f6e48145d45f6085c235ce8b57a25b",
      "sha1_git": "45f90c8abceec9eb6f1d15acf94d6e1877182056",
      "mime_type": "text/plain",
      "file_type": "ASCII text",
      "programming_language": "Rust",
      "is_binary": false,
      "is_text": true,
      "is_archive": false,
      "is_media": false,
      "is_source": true,
      "is_script": false,
      "detected_license_expression": null,
      "detected_license_expression_spdx": null,
      "license_detections": [],
      "license_clues": [],
      "percentage_of_license_text": 0,
      "copyrights": [],
      "holders": [],
      "authors": [],
      "files_count": 0,
      "dirs_count": 0,
      "size_count": 0,
      "scan_errors": []
    },
    {
      "path": "after/core-lib__src__util__path__29fcf4e8.rs",
      "type": "file",
      "name": "core-lib__src__util__path__29fcf4e8.rs",
      "base_name": "core-lib__src__util__path__29fcf4e8",
      "extension": ".rs",
      "size": 1774,
      "date": "2026-07-20",
      "sha1": "f371e282db3eeb2a937848e48a7f7b48a98ae104",
      "md5": "37b4c4c4110d044ee400332fabc96cce",
      "sha256": "1394829541f985ac2bcd375e3da0ea56be43aba336d36bb9ec6fdb0b62036adb",
      "sha1_git": "a98d28233a82bb68298098f31b8fcdbc8434604a",
      "mime_type": "text/x-asm",
      "file_type": "assembler source, ASCII text",
      "programming_language": "Rust",
      "is_binary": false,
      "is_text": true,
      "is_archive": false,
      "is_media": false,
      "is_source": true,
      "is_script": false,
      "detected_license_expression": null,
      "detected_license_expression_spdx": null,
      "license_detections": [],
      "license_clues": [],
      "percentage_of_license_text": 0,
      "copyrights": [],
      "holders": [],
      "authors": [],
      "files_count": 0,
      "dirs_count": 0,
      "size_count": 0,
      "scan_errors": []
    },
    {
      "path": "after/DEBUG__8d9790e0.md",
      "type": "file",
      "name": "DEBUG__8d9790e0.md",
      "base_name": "DEBUG__8d9790e0",
      "extension": ".md",
      "size": 2782,
      "date": "2026-07-20",
      "sha1": "d833e584b37abbd0b8ca0a74f0b4e034c9dd693f",
      "md5": "13d5f1bd53a06f8087ac886bcdc39479",
      "sha256": "51c37c0c5e2b1be54af3ef33b0caa19d2ac45d8ed9e12a972e2864bda4bba639",
      "sha1_git": "ae3790669de8d537495535fd23d065fb0c1257c6",
      "mime_type": "text/plain",
      "file_type": "ASCII text",
      "programming_language": null,
      "is_binary": false,
      "is_text": true,
      "is_archive": false,
      "is_media": false,
      "is_source": false,
      "is_script": false,
      "detected_license_expression": null,
      "detected_license_expression_spdx": null,
      "license_detections": [],
      "license_clues": [],
      "percentage_of_license_text": 0,
      "copyrights": [],
      "holders": [],
      "authors": [],
      "files_count": 0,
      "dirs_count": 0,
      "size_count": 0,
      "scan_errors": []
    },
    {
      "path": "after/exec-lib__Cargo__94cbdb9a.toml",
      "type": "file",
      "name": "exec-lib__Cargo__94cbdb9a.toml",
      "base_name": "exec-lib__Cargo__94cbdb9a",
      "extension": ".toml",
      "size": 573,
      "date": "2026-07-20",
      "sha1": "f55e75583cbb3c7f4155257e0b1cf21e7627e4f0",
      "md5": "00eb08bb2e83b7b647441ef904eda658",
      "sha256": "aefa0528a3570578ab92a0f2745f549893fe9f5eeda7d0ce92d956edb4ffe6e3",
      "sha1_git": "73d8a5c64f2752036f9d7dbe636ec9ff04c57308",
      "mime_type": "text/plain",
      "file_type": "ASCII text",
      "programming_language": null,
      "is_binary": false,
      "is_text": true,
      "is_archive": false,
      "is_media": false,
      "is_source": false,
      "is_script": false,
      "detected_license_expression": null,
      "detected_license_expression_spdx": null,
      "license_detections": [],
      "license_clues": [],
      "percentage_of_license_text": 0,
      "copyrights": [],
      "holders": [],
      "authors": [],
      "files_count": 0,
      "dirs_count": 0,
      "size_count": 0,
      "scan_errors": []
    },
    {
      "path": "after/exec-lib__src__listener__8763e188.rs",
      "type": "file",
      "name": "exec-lib__src__listener__8763e188.rs",
      "base_name": "exec-lib__src__listener__8763e188",
      "extension": ".rs",
      "size": 1160,
      "date": "2026-07-20",
      "sha1": "e93833f03c258206112b5c16404683b3aebbafa1",
      "md5": "249cb89d0b502c7c8f93e6ae3d1993b8",
      "sha256": "745e9ee2e24aafb9827fbc1c9eb8f54a4a5276c2a2aa5f5ec53879cfd694f4e8",
      "sha1_git": "f28250b23110da6d4e7e3e646fd546470343742e",
      "mime_type": "text/plain",
      "file_type": "ASCII text",
      "programming_language": "Rust",
      "is_binary": false,
      "is_text": true,
      "is_archive": false,
      "is_media": false,
      "is_source": true,
      "is_script": false,
      "detected_license_expression": null,
      "detected_license_expression_spdx": null,
      "license_detections": [],
      "license_clues": [],
      "percentage_of_license_text": 0,
      "copyrights": [],
      "holders": [],
      "authors": [],
      "files_count": 0,
      "dirs_count": 0,
      "size_count": 0,
      "scan_errors": []
    },
    {
      "path": "after/exec-lib__src__util__1451bdef.rs",
      "type": "file",
      "name": "exec-lib__src__util__1451bdef.rs",
      "base_name": "exec-lib__src__util__1451bdef",
      "extension": ".rs",
      "size": 5404,
      "date": "2026-07-20",
      "sha1": "d2787d42f0780971823b8614717680533e0fbe9e",
      "md5": "1086e50ac82e8348f37be0f41732f0eb",
      "sha256": "6953a5a36730b310013a0a871cddd1e27c2ad16592a5476fef52468605e805fe",
      "sha1_git": "3e808d33750c72f5f956128c815093e0e8cbbd5f",
      "mime_type": "text/plain",
      "file_type": "ASCII text",
      "programming_language": "Rust",
      "is_binary": false,
      "is_text": true,
      "is_archive": false,
      "is_media": false,
      "is_source": true,
      "is_script": false,
      "detected_license_expression": null,
      "detected_license_expression_spdx": null,
      "license_detections": [],
      "license_clues": [],
      "percentage_of_license_text": 0,
      "copyrights": [],
      "holders": [],
      "authors": [],
      "files_count": 0,
      "dirs_count": 0,
      "size_count": 0,
      "scan_errors": []
    },
    {
      "path": "after/launcher-lib__src__create__a863fe7b.rs",
      "type": "file",
      "name": "launcher-lib__src__create__a863fe7b.rs",
      "base_name": "launcher-lib__src__create__a863fe7b",
      "extension": ".rs",
      "size": 14171,
      "date": "2026-07-20",
      "sha1": "750dea572127634f7a9f4ee56ecfc348fddd8b5e",
      "md5": "f839f20f30eaa1da94fff9d411b05779",
      "sha256": "34221f85f999a0920e6d1eeb42ba82ba5e7f1f99daf2e9e9b023bf3c3ba7d3ef",
      "sha1_git": "bb308391e46c4469c4cedaff432c9ac9542ed379",
      "mime_type": "text/plain",
      "file_type": "ASCII text",
      "programming_language": "Rust",
      "is_binary": false,
      "is_text": true,
      "is_archive": false,
      "is_media": false,
      "is_source": true,
      "is_script": false,
      "detected_license_expression": null,
      "detected_license_expression_spdx": null,
      "license_detections": [],
      "license_clues": [],
      "percentage_of_license_text": 0,
      "copyrights": [],
      "holders": [],
      "authors": [],
      "files_count": 0,
      "dirs_count": 0,
      "size_count": 0,
      "scan_errors": []
    },
    {
      "path": "after/launcher-lib__src__plugins__applications__map__f1f40617.rs",
      "type": "file",
      "name": "launcher-lib__src__plugins__applications__map__f1f40617.rs",
      "base_name": "launcher-lib__src__plugins__applications__map__f1f40617",
      "extension": ".rs",
      "size": 5449,
      "date": "2026-07-20",
      "sha1": "0d65560f7ba8740af8487c921f942066ebe40a8d",
      "md5": "d70f8b3f5497f2a08000bc38b376bcb4",
      "sha256": "2e4fce7d33bc04fd6eb98b8631f054adc01a7e57c04331b65b6333bbe38cef29",
      "sha1_git": "afadf13de0bdc5a9cb1397d15558f7ee6402bd73",
      "mime_type": "text/plain",
      "file_type": "ASCII text",
      "programming_language": "Rust",
      "is_binary": false,
      "is_text": true,
      "is_archive": false,
      "is_media": false,
      "is_source": true,
      "is_script": false,
      "detected_license_expression": null,
      "detected_license_expression_spdx": null,
      "license_detections": [],
      "license_clues": [],
      "percentage_of_license_text": 0,
      "copyrights": [],
      "holders": [],
      "authors": [],
      "files_count": 0,
      "dirs_count": 0,
      "size_count": 0,
      "scan_errors": []
    },
    {
      "path": "after/launcher-lib__src__plugins__applications__plugin__9d07b056.rs",
      "type": "file",
      "name": "launcher-lib__src__plugins__applications__plugin__9d07b056.rs",
      "base_name": "launcher-lib__src__plugins__applications__plugin__9d07b056",
      "extension": ".rs",
      "size": 7889,
      "date": "2026-07-20",
      "sha1": "749d6d5af7dbd4a5bb27feb923aea96f953328c5",
      "md5": "b2ae147e15cdb808c7a2012976b0b7ae",
      "sha256": "a6b466df0d57cfe0a4f781252d0426f76949b2a6a4714e902a58e4a2cf62dbf8",
      "sha1_git": "7f0e9f590b99de32f8f6c9bec35cd2e25a77f42d",
      "mime_type": "text/plain",
      "file_type": "ASCII text",
      "programming_language": "Rust",
      "is_binary": false,
      "is_text": true,
      "is_archive": false,
      "is_media": false,
      "is_source": true,
      "is_script": false,
      "detected_license_expression": null,
      "detected_license_expression_spdx": null,
      "license_detections": [],
      "license_clues": [],
      "percentage_of_license_text": 0,
      "copyrights": [],
      "holders": [],
      "authors": [],
      "files_count": 0,
      "dirs_count": 0,
      "size_count": 0,
      "scan_errors": []
    },
    {
      "path": "after/launcher-lib__src__plugins__path__c731888c.rs",
      "type": "file",
      "name": "launcher-lib__src__plugins__path__c731888c.rs",
      "base_name": "launcher-lib__src__plugins__path__c731888c",
      "extension": ".rs",
      "size": 4170,
      "date": "2026-07-20",
      "sha1": "a98655d756348c25ebbe82fc1492ff13e8216e82",
      "md5": "14f375fa802da3ef522d0ff09215493d",
      "sha256": "2a46f847725461627d69d42a44a2c931900de2342eccd0f93571b78893e3a32b",
      "sha1_git": "7f89fa188697ef6bd557057fad55b6ae3ea9261d",
      "mime_type": "text/plain",
      "file_type": "ASCII text",
      "programming_language": "Rust",
      "is_binary": false,
      "is_text": true,
      "is_archive": false,
      "is_media": false,
      "is_source": true,
      "is_script": false,
      "detected_license_expression": null,
      "detected_license_expression_spdx": null,
      "license_detections": [],
      "license_clues": [],
      "percentage_of_license_text": 0,
      "copyrights": [],
      "holders": [],
      "authors": [],
      "files_count": 0,
      "dirs_count": 0,
      "size_count": 0,
      "scan_errors": []
    },
    {
      "path": "after/launcher-lib__src__plugins__search__default__40cf5c22.rs",
      "type": "file",
      "name": "launcher-lib__src__plugins__search__default__40cf5c22.rs",
      "base_name": "launcher-lib__src__plugins__search__default__40cf5c22",
      "extension": ".rs",
      "size": 2990,
      "date": "2026-07-20",
      "sha1": "cc829ac7b05cf714cd9edd4ac4a0193813e9f471",
      "md5": "83dae4fa6ad8fb67427517c8f714304b",
      "sha256": "8e416b77a0bd044dbc842ca7cbaa0105b01d6ed8554cbb29815e0279b2186bde",
      "sha1_git": "17f294abae0665052abb84ca9eb62b860560dbeb",
      "mime_type": "text/plain",
      "file_type": "ASCII text",
      "programming_language": "Rust",
      "is_binary": false,
      "is_text": true,
      "is_archive": false,
      "is_media": false,
      "is_source": true,
      "is_script": false,
      "detected_license_expression": null,
      "detected_license_expression_spdx": null,
      "license_detections": [],
      "license_clues": [],
      "percentage_of_license_text": 0,
      "copyrights": [],
      "holders": [],
      "authors": [],
      "files_count": 0,
      "dirs_count": 0,
      "size_count": 0,
      "scan_errors": []
    },
    {
      "path": "after/launcher-lib__src__plugins__search__mod__8565d9d2.rs",
      "type": "file",
      "name": "launcher-lib__src__plugins__search__mod__8565d9d2.rs",
      "base_name": "launcher-lib__src__plugins__search__mod__8565d9d2",
      "extension": ".rs",
      "size": 2579,
      "date": "2026-07-20",
      "sha1": "a86d3b42222d0422afc004886c5af5ce2cfd8f09",
      "md5": "4b78a2b86efe0fe19fca7d5502b6e7a1",
      "sha256": "16c33f88adab60da2544ec3f9791f44edded277dbc6be5f022982ae0e41f831c",
      "sha1_git": "92d56e40fbab0606ced7be920be61794d3994a02",
      "mime_type": "text/plain",
      "file_type": "ASCII text",
      "programming_language": "Rust",
      "is_binary": false,
      "is_text": true,
      "is_archive": false,
      "is_media": false,
      "is_source": true,
      "is_script": false,
      "detected_license_expression": null,
      "detected_license_expression_spdx": null,
      "license_detections": [],
      "license_clues": [],
      "percentage_of_license_text": 0,
      "copyrights": [],
      "holders": [],
      "authors": [],
      "files_count": 0,
      "dirs_count": 0,
      "size_count": 0,
      "scan_errors": []
    },
    {
      "path": "after/launcher-lib__src__plugins__shell__b11e40d1.rs",
      "type": "file",
      "name": "launcher-lib__src__plugins__shell__b11e40d1.rs",
      "base_name": "launcher-lib__src__plugins__shell__b11e40d1",
      "extension": ".rs",
      "size": 926,
      "date": "2026-07-20",
      "sha1": "13a64c5fa348f63b3c0bf8c78e0793194bd0a6b2",
      "md5": "3fb138aa27be7444d4d8ac2135010942",
      "sha256": "4f984618c7de55e859437c9b1e6b07181c58b6f92baf1e096882d71c68cffd50",
      "sha1_git": "e5b526c5019888d276b432223199422f4dcba928",
      "mime_type": "text/plain",
      "file_type": "ASCII text",
      "programming_language": "Rust",
      "is_binary": false,
      "is_text": true,
      "is_archive": false,
      "is_media": false,
      "is_source": true,
      "is_script": false,
      "detected_license_expression": null,
      "detected_license_expression_spdx": null,
      "license_detections": [],
      "license_clues": [],
      "percentage_of_license_text": 0,
      "copyrights": [],
      "holders": [],
      "authors": [],
      "files_count": 0,
      "dirs_count": 0,
      "size_count": 0,
      "scan_errors": []
    },
    {
      "path": "after/launcher-lib__src__plugins__terminal__5795653a.rs",
      "type": "file",
      "name": "launcher-lib__src__plugins__terminal__5795653a.rs",
      "base_name": "launcher-lib__src__plugins__terminal__5795653a",
      "extension": ".rs",
      "size": 1586,
      "date": "2026-07-20",
      "sha1": "519100e46b6bbf2cea4d2409a600c0438bd69905",
      "md5": "ca1a3d6c1169fd80dd3637f3dd4d9b6a",
      "sha256": "f887da79502fb34a620f4b547f9dd59b7a7b93b59a22a5791f862a2daf2684de",
      "sha1_git": "1a4a6e7082c12b7f8275379697a4d59d79b3de1a",
      "mime_type": "text/plain",
      "file_type": "ASCII text",
      "programming_language": "Rust",
      "is_binary": false,
      "is_text": true,
      "is_archive": false,
      "is_media": false,
      "is_source": true,
      "is_script": false,
      "detected_license_expression": null,
      "detected_license_expression_spdx": null,
      "license_detections": [],
      "license_clues": [],
      "percentage_of_license_text": 0,
      "copyrights": [],
      "holders": [],
      "authors": [],
      "files_count": 0,
      "dirs_count": 0,
      "size_count": 0,
      "scan_errors": []
    },
    {
      "path": "after/launcher-lib__src__update__69cf6692.rs",
      "type": "file",
      "name": "launcher-lib__src__update__69cf6692.rs",
      "base_name": "launcher-lib__src__update__69cf6692",
      "extension": ".rs",
      "size": 9290,
      "date": "2026-07-20",
      "sha1": "e4beab7a3f968b563c7a3f3e39df3ace3c008f49",
      "md5": "33b1517e444c38702f7ae13527cb7b9e",
      "sha256": "1d436d6859aba515262d979f662907ac5b0dbca00ab912ca5c0669093043d622",
      "sha1_git": "4c7b06a475808bde8e59726491f6a0415b20e4a0",
      "mime_type": "text/plain",
      "file_type": "ASCII text",
      "programming_language": "Rust",
      "is_binary": false,
      "is_text": true,
      "is_archive": false,
      "is_media": false,
      "is_source": true,
      "is_script": false,
      "detected_license_expression": null,
      "detected_license_expression_spdx": null,
      "license_detections": [],
      "license_clues": [],
      "percentage_of_license_text": 0,
      "copyrights": [],
      "holders": [],
      "authors": [],
      "files_count": 0,
      "dirs_count": 0,
      "size_count": 0,
      "scan_errors": []
    },
    {
      "path": "after/README__8ec9a00b.md",
      "type": "file",
      "name": "README__8ec9a00b.md",
      "base_name": "README__8ec9a00b",
      "extension": ".md",
      "size": 4152,
      "date": "2026-07-20",
      "sha1": "7ad26c7e8d7b0bed43a7b19f2273b9f0685ee955",
      "md5": "5d499ce683c64767641f1e7497d5faa8",
      "sha256": "4ca36c5cc0b14a9b0020d32e88007ecb7b278df5dda5307488f2a60e1ce31e14",
      "sha1_git": "4b458e9284cb292d863aeb6eb61f8af9eed207f2",
      "mime_type": "text/plain",
      "file_type": "ASCII text",
      "programming_language": null,
      "is_binary": false,
      "is_text": true,
      "is_archive": false,
      "is_media": false,
      "is_source": false,
      "is_script": false,
      "detected_license_expression": null,
      "detected_license_expression_spdx": null,
      "license_detections": [],
      "license_clues": [],
      "percentage_of_license_text": 0,
      "copyrights": [],
      "holders": [],
      "authors": [],
      "files_count": 0,
      "dirs_count": 0,
      "size_count": 0,
      "scan_errors": []
    },
    {
      "path": "after/src__cli__300934e5.rs",
      "type": "file",
      "name": "src__cli__300934e5.rs",
      "base_name": "src__cli__300934e5",
      "extension": ".rs",
      "size": 4755,
      "date": "2026-07-20",
      "sha1": "86729315ccccb455913151b0843b42b1f00dd8e1",
      "md5": "59464870c1a1cc9eb8b8108790720f2e",
      "sha256": "d821d9ee3762cb30d4cdee9614b46b8afdc68b4ce3b9c12149646677348a8477",
      "sha1_git": "48d04b47269d36d7a365d4d677ceca078716976c",
      "mime_type": "text/plain",
      "file_type": "ASCII text",
      "programming_language": "Rust",
      "is_binary": false,
      "is_text": true,
      "is_archive": false,
      "is_media": false,
      "is_source": true,
      "is_script": false,
      "detected_license_expression": null,
      "detected_license_expression_spdx": null,
      "license_detections": [],
      "license_clues": [],
      "percentage_of_license_text": 0,
      "copyrights": [],
      "holders": [],
      "authors": [],
      "files_count": 0,
      "dirs_count": 0,
      "size_count": 0,
      "scan_errors": []
    },
    {
      "path": "after/src__completions__64a4fa8b.rs",
      "type": "file",
      "name": "src__completions__64a4fa8b.rs",
      "base_name": "src__completions__64a4fa8b",
      "extension": ".rs",
      "size": 2086,
      "date": "2026-07-20",
      "sha1": "20f1a9dae48b3e0cfa2d7da05344acc8f0c3a4b0",
      "md5": "fd40c40231bccae6ce25cb5c976e71cb",
      "sha256": "b063f769af709fc31d6ff6895375a8478d3cc91be5c2ee766a02eceb557d7aa6",
      "sha1_git": "ba97a43d3196557cf310c310e52aa33f67dca401",
      "mime_type": "text/plain",
      "file_type": "ASCII text",
      "programming_language": "Rust",
      "is_binary": false,
      "is_text": true,
      "is_archive": false,
      "is_media": false,
      "is_source": true,
      "is_script": false,
      "detected_license_expression": null,
      "detected_license_expression_spdx": null,
      "license_detections": [],
      "license_clues": [],
      "percentage_of_license_text": 0,
      "copyrights": [],
      "holders": [],
      "authors": [],
      "files_count": 0,
      "dirs_count": 0,
      "size_count": 0,
      "scan_errors": []
    },
    {
      "path": "after/src__debug__4471a21c.rs",
      "type": "file",
      "name": "src__debug__4471a21c.rs",
      "base_name": "src__debug__4471a21c",
      "extension": ".rs",
      "size": 2366,
      "date": "2026-07-20",
      "sha1": "94ade39cffee9a5d575bd4576c0bdf9c6472410c",
      "md5": "0fc845c3818b6c4bf4411276921f96ba",
      "sha256": "5863822d4d80091ea2f82b346151f3ec9b02d5741f27e372d8cfe0af1fc31bdd",
      "sha1_git": "01e1dffb32aabfe15ce747fb1becf341300a10b0",
      "mime_type": "text/plain",
      "file_type": "ASCII text",
      "programming_language": "Rust",
      "is_binary": false,
      "is_text": true,
      "is_archive": false,
      "is_media": false,
      "is_source": true,
      "is_script": false,
      "detected_license_expression": null,
      "detected_license_expression_spdx": null,
      "license_detections": [],
      "license_clues": [],
      "percentage_of_license_text": 0,
      "copyrights": [],
      "holders": [],
      "authors": [],
      "files_count": 0,
      "dirs_count": 0,
      "size_count": 0,
      "scan_errors": []
    },
    {
      "path": "after/src__default_apps__77d7c9a9.rs",
      "type": "file",
      "name": "src__default_apps__77d7c9a9.rs",
      "base_name": "src__default_apps__77d7c9a9",
      "extension": ".rs",
      "size": 5481,
      "date": "2026-07-20",
      "sha1": "8d4e1e33ec05fdfbabc2d6d9a669f953025c05fd",
      "md5": "76358e31f607daba3e01711ac7cddd57",
      "sha256": "68c178cd977a7c27bb96ef8d5aadea923660db63a74a150316dd033ffb14c15b",
      "sha1_git": "4e6b99a0c25409e8155d63753a50933de55e1bfe",
      "mime_type": "text/plain",
      "file_type": "ASCII text",
      "programming_language": "Rust",
      "is_binary": false,
      "is_text": true,
      "is_archive": false,
      "is_media": false,
      "is_source": true,
      "is_script": false,
      "detected_license_expression": null,
      "detected_license_expression_spdx": null,
      "license_detections": [],
      "license_clues": [],
      "percentage_of_license_text": 0,
      "copyrights": [],
      "holders": [],
      "authors": [],
      "files_count": 0,
      "dirs_count": 0,
      "size_count": 0,
      "scan_errors": []
    },
    {
      "path": "after/src__keybinds__0130d648.rs",
      "type": "file",
      "name": "src__keybinds__0130d648.rs",
      "base_name": "src__keybinds__0130d648",
      "extension": ".rs",
      "size": 804,
      "date": "2026-07-20",
      "sha1": "338ad8cdc0f4cca4cc74bf0ce88a0cb084cda57d",
      "md5": "ca61f5334c80526a2b220decbe5cae99",
      "sha256": "b199d49dbcb93caf9768218b5861c97ed6db0a05ae0dfc65a5d5033d5c70a74b",
      "sha1_git": "76ec3e78e6020614a36e94a4053426ceba631c28",
      "mime_type": "text/plain",
      "file_type": "ASCII text",
      "programming_language": "Rust",
      "is_binary": false,
      "is_text": true,
      "is_archive": false,
      "is_media": false,
      "is_source": true,
      "is_script": false,
      "detected_license_expression": null,
      "detected_license_expression_spdx": null,
      "license_detections": [],
      "license_clues": [],
      "percentage_of_license_text": 0,
      "copyrights": [],
      "holders": [],
      "authors": [],
      "files_count": 0,
      "dirs_count": 0,
      "size_count": 0,
      "scan_errors": []
    },
    {
      "path": "after/src__main__4b569f42.rs",
      "type": "file",
      "name": "src__main__4b569f42.rs",
      "base_name": "src__main__4b569f42",
      "extension": ".rs",
      "size": 8171,
      "date": "2026-07-20",
      "sha1": "0b95ff05629f2a0c6a0e816f65e2222175d5b29a",
      "md5": "9fd85a26155eea236f0b83fa218a3039",
      "sha256": "f02431043402c0a34f40fa1ffa53a6527c9768d4d3ef9c19c5235f8fe2ae1456",
      "sha1_git": "1d4231dd3d1422520548013b1be36c2b42b4d4f0",
      "mime_type": "text/x-c",
      "file_type": "C source, ASCII text",
      "programming_language": "Rust",
      "is_binary": false,
      "is_text": true,
      "is_archive": false,
      "is_media": false,
      "is_source": true,
      "is_script": false,
      "detected_license_expression": null,
      "detected_license_expression_spdx": null,
      "license_detections": [],
      "license_clues": [],
      "percentage_of_license_text": 0,
      "copyrights": [],
      "holders": [],
      "authors": [],
      "files_count": 0,
      "dirs_count": 0,
      "size_count": 0,
      "scan_errors": []
    },
    {
      "path": "after/src__receive_handle__1f174813.rs",
      "type": "file",
      "name": "src__receive_handle__1f174813.rs",
      "base_name": "src__receive_handle__1f174813",
      "extension": ".rs",
      "size": 7557,
      "date": "2026-07-20",
      "sha1": "e1687c75884c99e829b679477cbe6d74b209a28f",
      "md5": "eebed139a138a26b253eca93d8216e80",
      "sha256": "03a3bfd2698334fbdbfe4410544c98d6057b2ddc4dcd67ebc251faf6b2994a0e",
      "sha1_git": "74ec8974cfa490aa3bfdc2542d2c0f3d7f07f509",
      "mime_type": "text/plain",
      "file_type": "ASCII text",
      "programming_language": "Rust",
      "is_binary": false,
      "is_text": true,
      "is_archive": false,
      "is_media": false,
      "is_source": true,
      "is_script": false,
      "detected_license_expression": null,
      "detected_license_expression_spdx": null,
      "license_detections": [],
      "license_clues": [],
      "percentage_of_license_text": 0,
      "copyrights": [],
      "holders": [],
      "authors": [],
      "files_count": 0,
      "dirs_count": 0,
      "size_count": 0,
      "scan_errors": []
    },
    {
      "path": "after/src__socket__02d79b85.rs",
      "type": "file",
      "name": "src__socket__02d79b85.rs",
      "base_name": "src__socket__02d79b85",
      "extension": ".rs",
      "size": 1733,
      "date": "2026-07-20",
      "sha1": "03d3f7d18e8e544fd4140d17bb17b2eda904280a",
      "md5": "cfb146ae07239402d324c5e7d35b3a6d",
      "sha256": "d88146d90b1d91ca1fc0e64c9a9ebd889a85f8275445b5ad8af2441c156bb307",
      "sha1_git": "633f3682e348587c09902ea9bc73f78f3357a6fb",
      "mime_type": "text/plain",
      "file_type": "ASCII text",
      "programming_language": "Rust",
      "is_binary": false,
      "is_text": true,
      "is_archive": false,
      "is_media": false,
      "is_source": true,
      "is_script": false,
      "detected_license_expression": null,
      "detected_license_expression_spdx": null,
      "license_detections": [],
      "license_clues": [],
      "percentage_of_license_text": 0,
      "copyrights": [],
      "holders": [],
      "authors": [],
      "files_count": 0,
      "dirs_count": 0,
      "size_count": 0,
      "scan_errors": []
    },
    {
      "path": "after/src__start__72bd440f.rs",
      "type": "file",
      "name": "src__start__72bd440f.rs",
      "base_name": "src__start__72bd440f",
      "extension": ".rs",
      "size": 10424,
      "date": "2026-07-20",
      "sha1": "fa1cbddf562ac7d53e8c583a2c8b440afcd793fe",
      "md5": "d67d3d7b4285d8785096ef1f626e389f",
      "sha256": "6d28027baeb9402eda492632b34c5d97a6fc1e0dd9dbed88c218e9d474206165",
      "sha1_git": "a7fcc4e4d9e95e64802b38300d324731ca2902ba",
      "mime_type": "text/plain",
      "file_type": "ASCII text",
      "programming_language": "Rust",
      "is_binary": false,
      "is_text": true,
      "is_archive": false,
      "is_media": false,
      "is_source": true,
      "is_script": false,
      "detected_license_expression": null,
      "detected_license_expression_spdx": null,
      "license_detections": [],
      "license_clues": [],
      "percentage_of_license_text": 0,
      "copyrights": [],
      "holders": [],
      "authors": [],
      "files_count": 0,
      "dirs_count": 0,
      "size_count": 0,
      "scan_errors": []
    },
    {
      "path": "after/src__util__71e2c87d.rs",
      "type": "file",
      "name": "src__util__71e2c87d.rs",
      "base_name": "src__util__71e2c87d",
      "extension": ".rs",
      "size": 2128,
      "date": "2026-07-20",
      "sha1": "80825bb48ad11aa604720646eb352c91c7570850",
      "md5": "25bb6b9b3fbdb0b1b434f1b6959a37a4",
      "sha256": "682367c23d0527597a087ff39fb5c2414e7f6460c5a534d9964c30a068208f8c",
      "sha1_git": "c6737e98547327f14e6d69c4a020eedea835509c",
      "mime_type": "text/plain",
      "file_type": "ASCII text",
      "programming_language": "Rust",
      "is_binary": false,
      "is_text": true,
      "is_archive": false,
      "is_media": false,
      "is_source": true,
      "is_script": false,
      "detected_license_expression": null,
      "detected_license_expression_spdx": null,
      "license_detections": [],
      "license_clues": [],
      "percentage_of_license_text": 0,
      "copyrights": [],
      "holders": [],
      "authors": [],
      "files_count": 0,
      "dirs_count": 0,
      "size_count": 0,
      "scan_errors": []
    },
    {
      "path": "after/windows-lib__src__desktop_map__fee6feb5.rs",
      "type": "file",
      "name": "windows-lib__src__desktop_map__fee6feb5.rs",
      "base_name": "windows-lib__src__desktop_map__fee6feb5",
      "extension": ".rs",
      "size": 5199,
      "date": "2026-07-20",
      "sha1": "260d084a47438789934f0fb6b65fa3eb13774d8f",
      "md5": "ada9dc969cdfe380f23d936b412cf00d",
      "sha256": "168c96630b834d4fc46fbca5ef6a1a5f227c03e71cf52df3402c8c25b8b9ccaf",
      "sha1_git": "427074b0a8b331f02547902c1e68c6fe0b1aa24c",
      "mime_type": "text/plain",
      "file_type": "ASCII text",
      "programming_language": "Rust",
      "is_binary": false,
      "is_text": true,
      "is_archive": false,
      "is_media": false,
      "is_source": true,
      "is_script": false,
      "detected_license_expression": null,
      "detected_license_expression_spdx": null,
      "license_detections": [],
      "license_clues": [],
      "percentage_of_license_text": 0,
      "copyrights": [],
      "holders": [],
      "authors": [],
      "files_count": 0,
      "dirs_count": 0,
      "size_count": 0,
      "scan_errors": []
    },
    {
      "path": "after/windows-lib__src__overview__close__baa8975c.rs",
      "type": "file",
      "name": "windows-lib__src__overview__close__baa8975c.rs",
      "base_name": "windows-lib__src__overview__close__baa8975c",
      "extension": ".rs",
      "size": 2878,
      "date": "2026-07-20",
      "sha1": "cdb5211b5e149f62bce594f2b2a16c34cbd16f9e",
      "md5": "a724d7c5cf9a0f0efbeeaab6b41a181f",
      "sha256": "015fb2a2b93d87a3d4819ced710ff542cbded13ba72af80b91a5387fa4ab55f2",
      "sha1_git": "c4f369fbb0c84f53fdc1cc9679f623cce74e0d65",
      "mime_type": "text/plain",
      "file_type": "ASCII text",
      "programming_language": "Rust",
      "is_binary": false,
      "is_text": true,
      "is_archive": false,
      "is_media": false,
      "is_source": true,
      "is_script": false,
      "detected_license_expression": null,
      "detected_license_expression_spdx": null,
      "license_detections": [],
      "license_clues": [],
      "percentage_of_license_text": 0,
      "copyrights": [],
      "holders": [],
      "authors": [],
      "files_count": 0,
      "dirs_count": 0,
      "size_count": 0,
      "scan_errors": []
    },
    {
      "path": "after/windows-lib__src__overview__open__ad3c9e55.rs",
      "type": "file",
      "name": "windows-lib__src__overview__open__ad3c9e55.rs",
      "base_name": "windows-lib__src__overview__open__ad3c9e55",
      "extension": ".rs",
      "size": 8592,
      "date": "2026-07-20",
      "sha1": "e49831c7d2996590dcc65b7619cd154cdc39e6b7",
      "md5": "74b00f6a570a78986534abf22222f7e9",
      "sha256": "14fe94c98445acc51232d56542625001c950f8db44d9aaba0fd6f20cc7c833c6",
      "sha1_git": "96bb7e8d98ac928989993f0a1f8b918e608bf80b",
      "mime_type": "text/plain",
      "file_type": "ASCII text",
      "programming_language": "Rust",
      "is_binary": false,
      "is_text": true,
      "is_archive": false,
      "is_media": false,
      "is_source": true,
      "is_script": false,
      "detected_license_expression": null,
      "detected_license_expression_spdx": null,
      "license_detections": [],
      "license_clues": [],
      "percentage_of_license_text": 0,
      "copyrights": [],
      "holders": [],
      "authors": [],
      "files_count": 0,
      "dirs_count": 0,
      "size_count": 0,
      "scan_errors": []
    },
    {
      "path": "after/windows-lib__src__overview__stop__0c2001ad.rs",
      "type": "file",
      "name": "windows-lib__src__overview__stop__0c2001ad.rs",
      "base_name": "windows-lib__src__overview__stop__0c2001ad",
      "extension": ".rs",
      "size": 485,
      "date": "2026-07-20",
      "sha1": "752a7d2c81bceed6d89dd743278afe1c1a34099d",
      "md5": "b46bb964c1b99b19090f813cb261f7d4",
      "sha256": "1f1dae36447c804b60e4ca91a79d45d6f0f51675dbb4b270f42c9289972b4629",
      "sha1_git": "d76913048da4b0892e89c4f395cacf5603698a13",
      "mime_type": "text/plain",
      "file_type": "ASCII text",
      "programming_language": "Rust",
      "is_binary": false,
      "is_text": true,
      "is_archive": false,
      "is_media": false,
      "is_source": true,
      "is_script": false,
      "detected_license_expression": null,
      "detected_license_expression_spdx": null,
      "license_detections": [],
      "license_clues": [],
      "percentage_of_license_text": 0,
      "copyrights": [],
      "holders": [],
      "authors": [],
      "files_count": 0,
      "dirs_count": 0,
      "size_count": 0,
      "scan_errors": []
    },
    {
      "path": "after/windows-lib__src__switch__close__2ba1b6b9.rs",
      "type": "file",
      "name": "windows-lib__src__switch__close__2ba1b6b9.rs",
      "base_name": "windows-lib__src__switch__close__2ba1b6b9",
      "extension": ".rs",
      "size": 1999,
      "date": "2026-07-20",
      "sha1": "498c2e7a54aca5894965b7f8fe7212cf629e2c6f",
      "md5": "34fa21293df5b8c30405bdef8e4bb54f",
      "sha256": "b45d1bb6f89667cbbb2c83eae5616e63425df42c77effcfb9bc23027fb11e788",
      "sha1_git": "8f7829ceadcee20c80a597e3240462d57698fe78",
      "mime_type": "text/plain",
      "file_type": "ASCII text",
      "programming_language": "Rust",
      "is_binary": false,
      "is_text": true,
      "is_archive": false,
      "is_media": false,
      "is_source": true,
      "is_script": false,
      "detected_license_expression": null,
      "detected_license_expression_spdx": null,
      "license_detections": [],
      "license_clues": [],
      "percentage_of_license_text": 0,
      "copyrights": [],
      "holders": [],
      "authors": [],
      "files_count": 0,
      "dirs_count": 0,
      "size_count": 0,
      "scan_errors": []
    },
    {
      "path": "after/windows-lib__src__switch__create__021645ad.rs",
      "type": "file",
      "name": "windows-lib__src__switch__create__021645ad.rs",
      "base_name": "windows-lib__src__switch__create__021645ad",
      "extension": ".rs",
      "size": 4607,
      "date": "2026-07-20",
      "sha1": "1a0a6b2d74d4fd1e280b393f48984483126e2459",
      "md5": "db07cae25bcbe3fbdc978c907c153582",
      "sha256": "172612e615f707110848851f84b0ce5ccec698c752512bf7133a1d5d1e01215e",
      "sha1_git": "65a91ca34568cd9e1463ffbe9c2b4c72ce6e6955",
      "mime_type": "text/plain",
      "file_type": "ASCII text",
      "programming_language": "Rust",
      "is_binary": false,
      "is_text": true,
      "is_archive": false,
      "is_media": false,
      "is_source": true,
      "is_script": false,
      "detected_license_expression": null,
      "detected_license_expression_spdx": null,
      "license_detections": [],
      "license_clues": [],
      "percentage_of_license_text": 0,
      "copyrights": [],
      "holders": [],
      "authors": [],
      "files_count": 0,
      "dirs_count": 0,
      "size_count": 0,
      "scan_errors": []
    },
    {
      "path": "after/windows-lib__src__switch__open__f7770294.rs",
      "type": "file",
      "name": "windows-lib__src__switch__open__f7770294.rs",
      "base_name": "windows-lib__src__switch__open__f7770294",
      "extension": ".rs",
      "size": 9808,
      "date": "2026-07-20",
      "sha1": "9e2c508b8e4a6397b7b920ec3d1b68d6072efbca",
      "md5": "fd2489cf224d0f8fc38be11830587102",
      "sha256": "a2da9febe96469719134e0854eb6f3ee45fa6dd2fc4e4e343b2db1cb996508c9",
      "sha1_git": "cdba0df47bc4d245cf870ddb68d39a8abbbb6fe8",
      "mime_type": "text/plain",
      "file_type": "ASCII text",
      "programming_language": "Rust",
      "is_binary": false,
      "is_text": true,
      "is_archive": false,
      "is_media": false,
      "is_source": true,
      "is_script": false,
      "detected_license_expression": null,
      "detected_license_expression_spdx": null,
      "license_detections": [],
      "license_clues": [],
      "percentage_of_license_text": 0,
      "copyrights": [],
      "holders": [],
      "authors": [],
      "files_count": 0,
      "dirs_count": 0,
      "size_count": 0,
      "scan_errors": []
    },
    {
      "path": "after/windows-lib__src__switch__stop__8cd15089.rs",
      "type": "file",
      "name": "windows-lib__src__switch__stop__8cd15089.rs",
      "base_name": "windows-lib__src__switch__stop__8cd15089",
      "extension": ".rs",
      "size": 424,
      "date": "2026-07-20",
      "sha1": "ebd1428ce9d70ab287b7c011c556fb279d4f62c0",
      "md5": "987b0cdc928b8420973718c06810e65f",
      "sha256": "03cb7a7c932b2ada4a0df8c26d8e34e9017aaad0099bd94af329614c4b434958",
      "sha1_git": "95c13e366e3442ada99a446cd0348e3d878c8b86",
      "mime_type": "text/plain",
      "file_type": "ASCII text",
      "programming_language": "Rust",
      "is_binary": false,
      "is_text": true,
      "is_archive": false,
      "is_media": false,
      "is_source": true,
      "is_script": false,
      "detected_license_expression": null,
      "detected_license_expression_spdx": null,
      "license_detections": [],
      "license_clues": [],
      "percentage_of_license_text": 0,
      "copyrights": [],
      "holders": [],
      "authors": [],
      "files_count": 0,
      "dirs_count": 0,
      "size_count": 0,
      "scan_errors": []
    }
  ]
}