{
  "headers": [
    {
      "tool_name": "scancode-toolkit",
      "tool_version": "32.5.0",
      "options": {
        "input": [
          "C:\\Users\\Bonelli\\PycharmProjects\\analisi-etica-codice-ai\\data\\files\\3246100058\\before"
        ],
        "--copyright": true,
        "--ignore": [
          "*vendor__*",
          "*node_modules__*",
          "*third_party__*",
          "*thirdparty__*",
          "*external__*",
          "*__proto__*",
          "*__generated__*",
          "*_pb2*",
          "*.pb.*",
          "*__gen__*",
          "*autogenerated*",
          "*auto_generated*",
          "*public__js__*",
          "*dist__*",
          "*build__*",
          "*__bundle*",
          "*.min.*"
        ],
        "--info": true,
        "--json-pp": "C:\\Users\\Bonelli\\PycharmProjects\\analisi-etica-codice-ai\\results\\ip_rights\\scancode_raw\\3246100058_before.json",
        "--license": true,
        "--processes": "6"
      },
      "notice": "Generated with ScanCode and provided on an \"AS IS\" BASIS, WITHOUT WARRANTIES\nOR CONDITIONS OF ANY KIND, either express or implied. No content created from\nScanCode should be considered or used as legal advice. Consult an Attorney\nfor any legal advice.\nScanCode is a free software code scanning tool from nexB Inc. and others.\nVisit https://github.com/nexB/scancode-toolkit/ for support and download.",
      "start_timestamp": "2026-07-23T014952.337313",
      "end_timestamp": "2026-07-23T015027.722199",
      "output_format_version": "4.1.0",
      "duration": 35.38551163673401,
      "message": null,
      "errors": [],
      "warnings": [],
      "extra_data": {
        "system_environment": {
          "operating_system": "win",
          "cpu_architecture": "64",
          "platform": "Windows-10-10.0.19045-SP0",
          "platform_version": "10.0.19045",
          "python_version": "3.14.6 (tags/v3.14.6:c63aec6, Jun 10 2026, 10:26:10) [MSC v.1944 64 bit (AMD64)]"
        },
        "spdx_license_list_version": "3.27",
        "files_count": 6
      }
    }
  ],
  "license_detections": [],
  "files": [
    {
      "path": "before",
      "type": "directory",
      "name": "before",
      "base_name": "before",
      "extension": "",
      "size": 0,
      "date": null,
      "sha1": null,
      "md5": null,
      "sha256": null,
      "sha1_git": null,
      "mime_type": null,
      "file_type": null,
      "programming_language": null,
      "is_binary": false,
      "is_text": false,
      "is_archive": false,
      "is_media": false,
      "is_source": false,
      "is_script": false,
      "detected_license_expression": null,
      "detected_license_expression_spdx": null,
      "license_detections": [],
      "license_clues": [],
      "percentage_of_license_text": 0,
      "copyrights": [],
      "holders": [],
      "authors": [],
      "files_count": 6,
      "dirs_count": 0,
      "size_count": 24811,
      "scan_errors": []
    },
    {
      "path": "before/tests__transpiler__x__swift__in_operator__afffb029.error",
      "type": "file",
      "name": "tests__transpiler__x__swift__in_operator__afffb029.error",
      "base_name": "tests__transpiler__x__swift__in_operator__afffb029",
      "extension": ".error",
      "size": 19,
      "date": "2026-07-20",
      "sha1": "f608b67c0fe128298ae2a36f0d7dbe09b595e45c",
      "md5": "a5918d8d4d8d3999cc5bd4cc4921505d",
      "sha256": "4a75b0d18fd8fda3be623b1bf181887152343e44de3c41495a4d5b61776753e0",
      "sha1_git": "7531a0e5494bcd50f63d81aebfd0cbc2a3a353d2",
      "mime_type": "text/plain",
      "file_type": "ASCII text, with no line terminators",
      "programming_language": null,
      "is_binary": false,
      "is_text": true,
      "is_archive": false,
      "is_media": false,
      "is_source": false,
      "is_script": false,
      "detected_license_expression": null,
      "detected_license_expression_spdx": null,
      "license_detections": [],
      "license_clues": [],
      "percentage_of_license_text": 0,
      "copyrights": [],
      "holders": [],
      "authors": [],
      "files_count": 0,
      "dirs_count": 0,
      "size_count": 0,
      "scan_errors": []
    },
    {
      "path": "before/tests__transpiler__x__swift__list_assign__758cfd2b.error",
      "type": "file",
      "name": "tests__transpiler__x__swift__list_assign__758cfd2b.error",
      "base_name": "tests__transpiler__x__swift__list_assign__758cfd2b",
      "extension": ".error",
      "size": 19,
      "date": "2026-07-20",
      "sha1": "f608b67c0fe128298ae2a36f0d7dbe09b595e45c",
      "md5": "a5918d8d4d8d3999cc5bd4cc4921505d",
      "sha256": "4a75b0d18fd8fda3be623b1bf181887152343e44de3c41495a4d5b61776753e0",
      "sha1_git": "7531a0e5494bcd50f63d81aebfd0cbc2a3a353d2",
      "mime_type": "text/plain",
      "file_type": "ASCII text, with no line terminators",
      "programming_language": null,
      "is_binary": false,
      "is_text": true,
      "is_archive": false,
      "is_media": false,
      "is_source": false,
      "is_script": false,
      "detected_license_expression": null,
      "detected_license_expression_spdx": null,
      "license_detections": [],
      "license_clues": [],
      "percentage_of_license_text": 0,
      "copyrights": [],
      "holders": [],
      "authors": [],
      "files_count": 0,
      "dirs_count": 0,
      "size_count": 0,
      "scan_errors": []
    },
    {
      "path": "before/tests__transpiler__x__swift__list_index__ffedd73c.error",
      "type": "file",
      "name": "tests__transpiler__x__swift__list_index__ffedd73c.error",
      "base_name": "tests__transpiler__x__swift__list_index__ffedd73c",
      "extension": ".error",
      "size": 19,
      "date": "2026-07-20",
      "sha1": "f608b67c0fe128298ae2a36f0d7dbe09b595e45c",
      "md5": "a5918d8d4d8d3999cc5bd4cc4921505d",
      "sha256": "4a75b0d18fd8fda3be623b1bf181887152343e44de3c41495a4d5b61776753e0",
      "sha1_git": "7531a0e5494bcd50f63d81aebfd0cbc2a3a353d2",
      "mime_type": "text/plain",
      "file_type": "ASCII text, with no line terminators",
      "programming_language": null,
      "is_binary": false,
      "is_text": true,
      "is_archive": false,
      "is_media": false,
      "is_source": false,
      "is_script": false,
      "detected_license_expression": null,
      "detected_license_expression_spdx": null,
      "license_detections": [],
      "license_clues": [],
      "percentage_of_license_text": 0,
      "copyrights": [],
      "holders": [],
      "authors": [],
      "files_count": 0,
      "dirs_count": 0,
      "size_count": 0,
      "scan_errors": []
    },
    {
      "path": "before/transpiler__x__swift__README__58e987f4.md",
      "type": "file",
      "name": "transpiler__x__swift__README__58e987f4.md",
      "base_name": "transpiler__x__swift__README__58e987f4",
      "extension": ".md",
      "size": 2298,
      "date": "2026-07-20",
      "sha1": "f9128e59588666c4882e8a71962c7216bfa10de8",
      "md5": "43aa7ab101cbed3d13d64134ab856df2",
      "sha256": "f2c62628e08f4a6d4b677a664f313ca39cf9b56bd6723c13b1c94612a6eb9640",
      "sha1_git": "5dedf92902208fcddc83ca1e55ce57ee0f1af5c3",
      "mime_type": "text/plain",
      "file_type": "ASCII text",
      "programming_language": null,
      "is_binary": false,
      "is_text": true,
      "is_archive": false,
      "is_media": false,
      "is_source": false,
      "is_script": false,
      "detected_license_expression": null,
      "detected_license_expression_spdx": null,
      "license_detections": [],
      "license_clues": [],
      "percentage_of_license_text": 0,
      "copyrights": [],
      "holders": [],
      "authors": [],
      "files_count": 0,
      "dirs_count": 0,
      "size_count": 0,
      "scan_errors": []
    },
    {
      "path": "before/transpiler__x__swift__TASKS__f31989f6.md",
      "type": "file",
      "name": "transpiler__x__swift__TASKS__f31989f6.md",
      "base_name": "transpiler__x__swift__TASKS__f31989f6",
      "extension": ".md",
      "size": 493,
      "date": "2026-07-20",
      "sha1": "6d8050f59ad9879399313f3ebb5b7b0c17930cdd",
      "md5": "0529330fca5e3bc8abce2bf3014938d6",
      "sha256": "88222d19baa63967db50cd72c524e1c02ec1baa8dbab996bea1fbe3fabccd11f",
      "sha1_git": "553beb742d6fd452d23c2952b32d868273c24714",
      "mime_type": "text/plain",
      "file_type": "ASCII text",
      "programming_language": null,
      "is_binary": false,
      "is_text": true,
      "is_archive": false,
      "is_media": false,
      "is_source": false,
      "is_script": false,
      "detected_license_expression": null,
      "detected_license_expression_spdx": null,
      "license_detections": [],
      "license_clues": [],
      "percentage_of_license_text": 0,
      "copyrights": [],
      "holders": [],
      "authors": [],
      "files_count": 0,
      "dirs_count": 0,
      "size_count": 0,
      "scan_errors": []
    },
    {
      "path": "before/transpiler__x__swift__transpiler__f037b3d0.go",
      "type": "file",
      "name": "transpiler__x__swift__transpiler__f037b3d0.go",
      "base_name": "transpiler__x__swift__transpiler__f037b3d0",
      "extension": ".go",
      "size": 21963,
      "date": "2026-07-20",
      "sha1": "e0184e6f85567366738c1af78bc6f6972c0e1245",
      "md5": "04debb6349ea0b125df9b21a35619bab",
      "sha256": "7b94ddfb625291e63bb7f6fdda433cbcacbfc8406c7ff24342ddb3401ea141e9",
      "sha1_git": "ff1e647e856f37e25d7bb4f7b8f658c12931c341",
      "mime_type": "text/plain",
      "file_type": "ASCII text",
      "programming_language": "Go",
      "is_binary": false,
      "is_text": true,
      "is_archive": false,
      "is_media": false,
      "is_source": true,
      "is_script": false,
      "detected_license_expression": null,
      "detected_license_expression_spdx": null,
      "license_detections": [],
      "license_clues": [],
      "percentage_of_license_text": 0,
      "copyrights": [],
      "holders": [],
      "authors": [],
      "files_count": 0,
      "dirs_count": 0,
      "size_count": 0,
      "scan_errors": []
    }
  ]
}