{
  "headers": [
    {
      "tool_name": "scancode-toolkit",
      "tool_version": "32.5.0",
      "options": {
        "input": [
          "C:\\Users\\Bonelli\\PycharmProjects\\analisi-etica-codice-ai\\data\\files\\3258270000\\after"
        ],
        "--copyright": true,
        "--ignore": [
          "*vendor__*",
          "*node_modules__*",
          "*third_party__*",
          "*thirdparty__*",
          "*external__*",
          "*__proto__*",
          "*__generated__*",
          "*_pb2*",
          "*.pb.*",
          "*__gen__*",
          "*autogenerated*",
          "*auto_generated*",
          "*public__js__*",
          "*dist__*",
          "*build__*",
          "*__bundle*",
          "*.min.*"
        ],
        "--info": true,
        "--json-pp": "C:\\Users\\Bonelli\\PycharmProjects\\analisi-etica-codice-ai\\results\\ip_rights\\scancode_raw\\3258270000.json",
        "--license": true,
        "--processes": "2"
      },
      "notice": "Generated with ScanCode and provided on an \"AS IS\" BASIS, WITHOUT WARRANTIES\nOR CONDITIONS OF ANY KIND, either express or implied. No content created from\nScanCode should be considered or used as legal advice. Consult an Attorney\nfor any legal advice.\nScanCode is a free software code scanning tool from nexB Inc. and others.\nVisit https://github.com/nexB/scancode-toolkit/ for support and download.",
      "start_timestamp": "2026-07-22T100906.798220",
      "end_timestamp": "2026-07-22T100918.189842",
      "output_format_version": "4.1.0",
      "duration": 11.391637325286865,
      "message": null,
      "errors": [],
      "warnings": [],
      "extra_data": {
        "system_environment": {
          "operating_system": "win",
          "cpu_architecture": "64",
          "platform": "Windows-10-10.0.19045-SP0",
          "platform_version": "10.0.19045",
          "python_version": "3.14.6 (tags/v3.14.6:c63aec6, Jun 10 2026, 10:26:10) [MSC v.1944 64 bit (AMD64)]"
        },
        "spdx_license_list_version": "3.27",
        "files_count": 11
      }
    }
  ],
  "license_detections": [],
  "files": [
    {
      "path": "after",
      "type": "directory",
      "name": "after",
      "base_name": "after",
      "extension": "",
      "size": 0,
      "date": null,
      "sha1": null,
      "md5": null,
      "sha256": null,
      "sha1_git": null,
      "mime_type": null,
      "file_type": null,
      "programming_language": null,
      "is_binary": false,
      "is_text": false,
      "is_archive": false,
      "is_media": false,
      "is_source": false,
      "is_script": false,
      "detected_license_expression": null,
      "detected_license_expression_spdx": null,
      "license_detections": [],
      "license_clues": [],
      "percentage_of_license_text": 0,
      "copyrights": [],
      "holders": [],
      "authors": [],
      "files_count": 11,
      "dirs_count": 0,
      "size_count": 118629,
      "scan_errors": []
    },
    {
      "path": "after/openagents-tauri__bun__d2b11d5c.lock",
      "type": "file",
      "name": "openagents-tauri__bun__d2b11d5c.lock",
      "base_name": "openagents-tauri__bun__d2b11d5c",
      "extension": ".lock",
      "size": 75004,
      "date": "2026-07-20",
      "sha1": "6c03dc68f273150bcfe1c6a10d7f26afb49671ea",
      "md5": "d73ec0153c419f217c576c34925f29c9",
      "sha256": "2976ed50ceb92f428bf20786a04b845287d2d3480e7969c9d91424b7738c8e3c",
      "sha1_git": "5103c9516695908808835c5df5a6db0455cf154d",
      "mime_type": "application/json",
      "file_type": "JSON data",
      "programming_language": null,
      "is_binary": false,
      "is_text": true,
      "is_archive": false,
      "is_media": false,
      "is_source": false,
      "is_script": false,
      "detected_license_expression": null,
      "detected_license_expression_spdx": null,
      "license_detections": [],
      "license_clues": [],
      "percentage_of_license_text": 0,
      "copyrights": [],
      "holders": [],
      "authors": [],
      "files_count": 0,
      "dirs_count": 0,
      "size_count": 0,
      "scan_errors": []
    },
    {
      "path": "after/openagents-tauri__package__063f9650.json",
      "type": "file",
      "name": "openagents-tauri__package__063f9650.json",
      "base_name": "openagents-tauri__package__063f9650",
      "extension": ".json",
      "size": 1135,
      "date": "2026-07-20",
      "sha1": "cdebf1de5e73cf0533c3295e0f8fb0f86b7baf9b",
      "md5": "02643211ba44daa589519d27e06972d4",
      "sha256": "66d22acf8a6275523b7e55ecc140c40100bc785486ad0173a491188dc6c1ac81",
      "sha1_git": "7f3267cf93030f98ff814b474deb922d0bcb45c7",
      "mime_type": "application/json",
      "file_type": "JSON data",
      "programming_language": null,
      "is_binary": false,
      "is_text": true,
      "is_archive": false,
      "is_media": false,
      "is_source": false,
      "is_script": false,
      "detected_license_expression": null,
      "detected_license_expression_spdx": null,
      "license_detections": [],
      "license_clues": [],
      "percentage_of_license_text": 0,
      "copyrights": [],
      "holders": [],
      "authors": [],
      "files_count": 0,
      "dirs_count": 0,
      "size_count": 0,
      "scan_errors": []
    },
    {
      "path": "after/openagents-tauri__src__App__959fbdd6.tsx",
      "type": "file",
      "name": "openagents-tauri__src__App__959fbdd6.tsx",
      "base_name": "openagents-tauri__src__App__959fbdd6",
      "extension": ".tsx",
      "size": 10140,
      "date": "2026-07-20",
      "sha1": "2d41c1ccad1662474064c1daf5622102e61adf6e",
      "md5": "2193ae738ea69b72dcd7ad67f2cfd788",
      "sha256": "d99e1144e28f07ade4ab12c741ea2860ac74495f80b53c7678e9c27bfa9a0189",
      "sha1_git": "7a38766f2e124549dd1efa3a933f2cfb1ee36b23",
      "mime_type": "text/x-java",
      "file_type": "Java source, ASCII text",
      "programming_language": "TypeScript",
      "is_binary": false,
      "is_text": true,
      "is_archive": false,
      "is_media": false,
      "is_source": true,
      "is_script": false,
      "detected_license_expression": null,
      "detected_license_expression_spdx": null,
      "license_detections": [],
      "license_clues": [],
      "percentage_of_license_text": 0,
      "copyrights": [],
      "holders": [],
      "authors": [],
      "files_count": 0,
      "dirs_count": 0,
      "size_count": 0,
      "scan_errors": []
    },
    {
      "path": "after/openagents-tauri__src__components__hud__Hotbar__a6358998.tsx",
      "type": "file",
      "name": "openagents-tauri__src__components__hud__Hotbar__a6358998.tsx",
      "base_name": "openagents-tauri__src__components__hud__Hotbar__a6358998",
      "extension": ".tsx",
      "size": 2427,
      "date": "2026-07-20",
      "sha1": "0be437a3055c34580da00e620a57cb25be41086b",
      "md5": "5591a37b6af2d2a06f4f4e9e8ce33ee1",
      "sha256": "e53179e640932f43395b948e22cacefaf5ae95d9a437c823ceeabd8c8a440746",
      "sha1_git": "d8e3534e39c7a6525a1b08d483490055fd809df1",
      "mime_type": "text/x-java",
      "file_type": "Java source, ASCII text",
      "programming_language": "TypeScript",
      "is_binary": false,
      "is_text": true,
      "is_archive": false,
      "is_media": false,
      "is_source": true,
      "is_script": false,
      "detected_license_expression": null,
      "detected_license_expression_spdx": null,
      "license_detections": [],
      "license_clues": [],
      "percentage_of_license_text": 0,
      "copyrights": [],
      "holders": [],
      "authors": [],
      "files_count": 0,
      "dirs_count": 0,
      "size_count": 0,
      "scan_errors": []
    },
    {
      "path": "after/openagents-tauri__src__components__hud__HotbarItem__c17915d2.tsx",
      "type": "file",
      "name": "openagents-tauri__src__components__hud__HotbarItem__c17915d2.tsx",
      "base_name": "openagents-tauri__src__components__hud__HotbarItem__c17915d2",
      "extension": ".tsx",
      "size": 2001,
      "date": "2026-07-20",
      "sha1": "25023ea5a888907eb7b33538f14507183b707939",
      "md5": "59aacfb941e9b489c93d18972e2b9832",
      "sha256": "ce70bc67996550aa10a221421849bd0917899cc3507a51a85672f006db281b0b",
      "sha1_git": "a7e5271a5f1ef65ff0f01945daef4ef6f5e94f86",
      "mime_type": "text/x-java",
      "file_type": "Java source, UTF-8 Unicode text",
      "programming_language": "TypeScript",
      "is_binary": false,
      "is_text": true,
      "is_archive": false,
      "is_media": false,
      "is_source": true,
      "is_script": false,
      "detected_license_expression": null,
      "detected_license_expression_spdx": null,
      "license_detections": [],
      "license_clues": [],
      "percentage_of_license_text": 0,
      "copyrights": [],
      "holders": [],
      "authors": [],
      "files_count": 0,
      "dirs_count": 0,
      "size_count": 0,
      "scan_errors": []
    },
    {
      "path": "after/openagents-tauri__src__panes__ChatPane__5e986717.tsx",
      "type": "file",
      "name": "openagents-tauri__src__panes__ChatPane__5e986717.tsx",
      "base_name": "openagents-tauri__src__panes__ChatPane__5e986717",
      "extension": ".tsx",
      "size": 3794,
      "date": "2026-07-20",
      "sha1": "63e9f1a394f01f1881e237dd3146771fb694cb63",
      "md5": "923cd3ffa42e54af2adcd77bc0b40a13",
      "sha256": "76f6efb45ff54ad971fac2b3ec28a8d7401ad6570784afe0c6f0ac034d4b0f27",
      "sha1_git": "dd2ed529a3feecda50ce8a062afc1f39f5f005c3",
      "mime_type": "text/x-java",
      "file_type": "Java source, ASCII text",
      "programming_language": "TypeScript",
      "is_binary": false,
      "is_text": true,
      "is_archive": false,
      "is_media": false,
      "is_source": true,
      "is_script": false,
      "detected_license_expression": null,
      "detected_license_expression_spdx": null,
      "license_detections": [],
      "license_clues": [],
      "percentage_of_license_text": 0,
      "copyrights": [],
      "holders": [],
      "authors": [],
      "files_count": 0,
      "dirs_count": 0,
      "size_count": 0,
      "scan_errors": []
    },
    {
      "path": "after/openagents-tauri__src__panes__MetadataPane__ddbc120a.tsx",
      "type": "file",
      "name": "openagents-tauri__src__panes__MetadataPane__ddbc120a.tsx",
      "base_name": "openagents-tauri__src__panes__MetadataPane__ddbc120a",
      "extension": ".tsx",
      "size": 3609,
      "date": "2026-07-20",
      "sha1": "d38f13615c143e51cb91f076e53e1c7c81e3a5b6",
      "md5": "cd0581443050494593cce8f0a7dd45b2",
      "sha256": "db41a27fdcc17212de803fcdd5953dcc35baf6492f487ea6210fbe12c4c0621d",
      "sha1_git": "c7f476346b3a3ec36ec85511408ac1d50bd7fdfe",
      "mime_type": "text/x-java",
      "file_type": "Java source, UTF-8 Unicode text",
      "programming_language": "TypeScript",
      "is_binary": false,
      "is_text": true,
      "is_archive": false,
      "is_media": false,
      "is_source": true,
      "is_script": false,
      "detected_license_expression": null,
      "detected_license_expression_spdx": null,
      "license_detections": [],
      "license_clues": [],
      "percentage_of_license_text": 0,
      "copyrights": [],
      "holders": [],
      "authors": [],
      "files_count": 0,
      "dirs_count": 0,
      "size_count": 0,
      "scan_errors": []
    },
    {
      "path": "after/openagents-tauri__src__panes__Pane__a892868f.tsx",
      "type": "file",
      "name": "openagents-tauri__src__panes__Pane__a892868f.tsx",
      "base_name": "openagents-tauri__src__panes__Pane__a892868f",
      "extension": ".tsx",
      "size": 10438,
      "date": "2026-07-20",
      "sha1": "556fde12a01131216128af312979bebb38ca1b0f",
      "md5": "9f06b7ce607c90dd1b8160ae10617e2a",
      "sha256": "d7f0ed45d17ba58ba40cf14917faba26993903b1b51d7491a1b178eaeb6e49a5",
      "sha1_git": "b208b99087ff65f1cf67a31b177b427f64604a85",
      "mime_type": "text/x-java",
      "file_type": "Java source, ASCII text",
      "programming_language": "TypeScript",
      "is_binary": false,
      "is_text": true,
      "is_archive": false,
      "is_media": false,
      "is_source": true,
      "is_script": false,
      "detected_license_expression": null,
      "detected_license_expression_spdx": null,
      "license_detections": [],
      "license_clues": [],
      "percentage_of_license_text": 0,
      "copyrights": [],
      "holders": [],
      "authors": [],
      "files_count": 0,
      "dirs_count": 0,
      "size_count": 0,
      "scan_errors": []
    },
    {
      "path": "after/openagents-tauri__src__panes__PaneManager__761ff298.tsx",
      "type": "file",
      "name": "openagents-tauri__src__panes__PaneManager__761ff298.tsx",
      "base_name": "openagents-tauri__src__panes__PaneManager__761ff298",
      "extension": ".tsx",
      "size": 1678,
      "date": "2026-07-20",
      "sha1": "a2c448d6bd0bf46d8c0290055a90fa4d7c724dbf",
      "md5": "9c3ebd36e9d558263df6a6f6dc254b77",
      "sha256": "f367a4dafa492a0e96a5efdab7df387e1d0b4af778ea9e0b59b35e53a728b4ee",
      "sha1_git": "78816bc0cd9d8839786c06133e22037276c32a0e",
      "mime_type": "text/x-java",
      "file_type": "Java source, ASCII text",
      "programming_language": "TypeScript",
      "is_binary": false,
      "is_text": true,
      "is_archive": false,
      "is_media": false,
      "is_source": true,
      "is_script": false,
      "detected_license_expression": null,
      "detected_license_expression_spdx": null,
      "license_detections": [],
      "license_clues": [],
      "percentage_of_license_text": 0,
      "copyrights": [],
      "holders": [],
      "authors": [],
      "files_count": 0,
      "dirs_count": 0,
      "size_count": 0,
      "scan_errors": []
    },
    {
      "path": "after/openagents-tauri__src__stores__pane__879265b6.ts",
      "type": "file",
      "name": "openagents-tauri__src__stores__pane__879265b6.ts",
      "base_name": "openagents-tauri__src__stores__pane__879265b6",
      "extension": ".ts",
      "size": 7013,
      "date": "2026-07-20",
      "sha1": "4eb8c0567590cedc230efcba74968fb53de946c0",
      "md5": "d5595a14dfc79d3cf416b358a0b490ad",
      "sha256": "b4784851681a6e4e035cd3a9b091e8942c0c624333610d6ad1e792f742ba6466",
      "sha1_git": "1f2974d175e88da0c46d004b95bfabc8dbe30dea",
      "mime_type": "text/x-java",
      "file_type": "Java source, ASCII text",
      "programming_language": "TypeScript",
      "is_binary": false,
      "is_text": true,
      "is_archive": false,
      "is_media": false,
      "is_source": true,
      "is_script": false,
      "detected_license_expression": null,
      "detected_license_expression_spdx": null,
      "license_detections": [],
      "license_clues": [],
      "percentage_of_license_text": 0,
      "copyrights": [],
      "holders": [],
      "authors": [],
      "files_count": 0,
      "dirs_count": 0,
      "size_count": 0,
      "scan_errors": []
    },
    {
      "path": "after/openagents-tauri__src__types__pane__a9f0cadc.ts",
      "type": "file",
      "name": "openagents-tauri__src__types__pane__a9f0cadc.ts",
      "base_name": "openagents-tauri__src__types__pane__a9f0cadc",
      "extension": ".ts",
      "size": 1390,
      "date": "2026-07-20",
      "sha1": "366b8cc7a8321d6f9de11ab642d39eb847f72431",
      "md5": "b0c2aca19924af221242d30efb83b04c",
      "sha256": "be47ea1f72a07bfaec5c87297c4b18891655e16100b11db7fd443aea56d924cb",
      "sha1_git": "187924a76b44dba5c26d925d29608757915e569c",
      "mime_type": "text/plain",
      "file_type": "ASCII text",
      "programming_language": "TypeScript",
      "is_binary": false,
      "is_text": true,
      "is_archive": false,
      "is_media": false,
      "is_source": true,
      "is_script": false,
      "detected_license_expression": null,
      "detected_license_expression_spdx": null,
      "license_detections": [],
      "license_clues": [],
      "percentage_of_license_text": 0,
      "copyrights": [],
      "holders": [],
      "authors": [],
      "files_count": 0,
      "dirs_count": 0,
      "size_count": 0,
      "scan_errors": []
    }
  ]
}